README.md
setup.cfg
setup.py
dsnd_probability_eunbee/Binomialdistribution.py
dsnd_probability_eunbee/Gaussiandistribution.py
dsnd_probability_eunbee/Generaldistribution.py
dsnd_probability_eunbee/__init__.py
dsnd_probability_eunbee.egg-info/PKG-INFO
dsnd_probability_eunbee.egg-info/SOURCES.txt
dsnd_probability_eunbee.egg-info/dependency_links.txt
dsnd_probability_eunbee.egg-info/not-zip-safe
dsnd_probability_eunbee.egg-info/top_level.txt